README.rst
setup.py
pqueue/__init__.py
pqueue/pqueue.py
pqueue.egg-info/PKG-INFO
pqueue.egg-info/SOURCES.txt
pqueue.egg-info/dependency_links.txt
pqueue.egg-info/top_level.txt
pqueue/tests/__init__.py
pqueue/tests/test_queue.py