Metadata-Version: 1.1
Name: pqueue
Version: 0.1.2
Summary: A single process, persistent multi-producer, multi-consumer queue.
Home-page: http://github.com/balena/python-pqueue
Author: G. B. Versiani
Author-email: guibv@yahoo.com
License: BSD
Platform: all
Classifier: Development Status :: 4 - Beta
Classifier: Operating System :: OS Independent
Classifier: Intended Audience :: Developers
Classifier: License :: OSI Approved :: BSD License
Classifier: Programming Language :: Python :: 2
Classifier: Programming Language :: Python :: 2.7
Classifier: Programming Language :: Python :: 3
Classifier: Programming Language :: Python :: 3.3
Classifier: Topic :: Software Development :: Libraries
